<?xml version="1.0"?>
<G2_Editor_settings>
  <G2_Synth_1>
    <Editor_settings LedColor="65280" LogEnabled="True" OnlyTextMenus="False" CableThickness="2" HighlightColor="16776960" SlotStripColor="4341694" SlotStripInverseColor="5447424" SlotStripDisabledColor="13684944"/>
    <TCP_settings IP="127.0.0.1" Port="2501" IsServer="True" TimerBroadcastLedMessages="500"/>
    <MIDI_settings MidiInDevice="" MidiOutDevice=""/>
  </G2_Synth_1>
  <CTRL_MIDI_in_device_list>
    <CtrlMidiDevice CtrlMidiDevice="BCR2000" CtrlMidiEnabled="True"/>
  </CTRL_MIDI_in_device_list>
  <CTRL_MIDI_out_device_list>
    <CtrlMidiDevice CtrlMidiDevice="BCR2000" CtrlMidiEnabled="True"/>
  </CTRL_MIDI_out_device_list>
  <CTRL_MIDI_ASSIGNMENT_LIST>
    <CTRL_MIDI_ASSIGNMENT CC="42" Note="0" Channel="0" MaxValue="127" MinValue="0" ControlPath="/frmParameterPages/skP3" ControlIndex="0"/>
    <CTRL_MIDI_ASSIGNMENT CC="43" Note="0" Channel="0" MaxValue="127" MinValue="0" ControlPath="/frmParameterPages/skP4" ControlIndex="0"/>
    <CTRL_MIDI_ASSIGNMENT CC="44" Note="0" Channel="0" MaxValue="127" MinValue="0" ControlPath="/frmParameterPages/skP5" ControlIndex="0"/>
    <CTRL_MIDI_ASSIGNMENT CC="45" Note="0" Channel="0" MaxValue="127" MinValue="0" ControlPath="/frmParameterPages/skP6" ControlIndex="0"/>
    <CTRL_MIDI_ASSIGNMENT CC="46" Note="0" Channel="0" MaxValue="127" MinValue="0" ControlPath="/frmParameterPages/skP7" ControlIndex="0"/>
    <CTRL_MIDI_ASSIGNMENT CC="41" Note="0" Channel="0" MaxValue="127" MinValue="0" ControlPath="/frmParameterPages/skP2" ControlIndex="0"/>
    <CTRL_MIDI_ASSIGNMENT CC="49" Note="0" Channel="0" MaxValue="127" MinValue="0" ControlPath="/frmParameterPages/bfP2" ControlIndex="0"/>
    <CTRL_MIDI_ASSIGNMENT CC="50" Note="0" Channel="0" MaxValue="127" MinValue="0" ControlPath="/frmParameterPages/bfP3" ControlIndex="0"/>
    <CTRL_MIDI_ASSIGNMENT CC="51" Note="0" Channel="0" MaxValue="127" MinValue="0" ControlPath="/frmParameterPages/bfP4" ControlIndex="0"/>
    <CTRL_MIDI_ASSIGNMENT CC="52" Note="0" Channel="0" MaxValue="127" MinValue="0" ControlPath="/frmParameterPages/bfP5" ControlIndex="0"/>
    <CTRL_MIDI_ASSIGNMENT CC="53" Note="0" Channel="0" MaxValue="127" MinValue="0" ControlPath="/frmParameterPages/bfP6" ControlIndex="0"/>
    <CTRL_MIDI_ASSIGNMENT CC="54" Note="0" Channel="0" MaxValue="127" MinValue="0" ControlPath="/frmParameterPages/bfP7" ControlIndex="0"/>
    <CTRL_MIDI_ASSIGNMENT CC="55" Note="0" Channel="0" MaxValue="127" MinValue="0" ControlPath="/frmParameterPages/bfP8" ControlIndex="0"/>
    <CTRL_MIDI_ASSIGNMENT CC="48" Note="0" Channel="0" MaxValue="127" MinValue="0" ControlPath="/frmParameterPages/bfP1" ControlIndex="0"/>
    <CTRL_MIDI_ASSIGNMENT CC="56" Note="0" Channel="0" MaxValue="127" MinValue="0" ControlPath="/frmParameterPages/pBottom/rbVariation" ControlIndex="0"/>
    <CTRL_MIDI_ASSIGNMENT CC="57" Note="0" Channel="0" MaxValue="127" MinValue="0" ControlPath="/frmParameterPages/pBottom/rbVariation" ControlIndex="1"/>
    <CTRL_MIDI_ASSIGNMENT CC="58" Note="0" Channel="0" MaxValue="127" MinValue="0" ControlPath="/frmParameterPages/pBottom/rbVariation" ControlIndex="2"/>
    <CTRL_MIDI_ASSIGNMENT CC="59" Note="0" Channel="0" MaxValue="127" MinValue="0" ControlPath="/frmParameterPages/pBottom/rbVariation" ControlIndex="3"/>
    <CTRL_MIDI_ASSIGNMENT CC="60" Note="0" Channel="0" MaxValue="127" MinValue="0" ControlPath="/frmParameterPages/pBottom/rbVariation" ControlIndex="4"/>
    <CTRL_MIDI_ASSIGNMENT CC="61" Note="0" Channel="0" MaxValue="127" MinValue="0" ControlPath="/frmParameterPages/pBottom/rbVariation" ControlIndex="5"/>
    <CTRL_MIDI_ASSIGNMENT CC="62" Note="0" Channel="0" MaxValue="127" MinValue="0" ControlPath="/frmParameterPages/pBottom/rbVariation" ControlIndex="6"/>
    <CTRL_MIDI_ASSIGNMENT CC="63" Note="0" Channel="0" MaxValue="127" MinValue="0" ControlPath="/frmParameterPages/pBottom/rbVariation" ControlIndex="7"/>
    <CTRL_MIDI_ASSIGNMENT CC="105" Note="0" Channel="0" MaxValue="127" MinValue="0" ControlPath="/frmParameterPages/pBottom/rbMode" ControlIndex="0"/>
    <CTRL_MIDI_ASSIGNMENT CC="106" Note="0" Channel="0" MaxValue="127" MinValue="0" ControlPath="/frmParameterPages/pBottom/rbMode" ControlIndex="1"/>
    <CTRL_MIDI_ASSIGNMENT CC="107" Note="0" Channel="0" MaxValue="127" MinValue="0" ControlPath="/frmParameterPages/pBottom/rbMode" ControlIndex="2"/>
    <CTRL_MIDI_ASSIGNMENT CC="108" Note="0" Channel="0" MaxValue="127" MinValue="0" ControlPath="/frmParameterPages/pBottom/rbMode" ControlIndex="3"/>
    <CTRL_MIDI_ASSIGNMENT CC="32" Note="0" Channel="0" MaxValue="127" MinValue="0" ControlPath="/frmParameterPages/pRight/rbParamPage" ControlIndex="0"/>
    <CTRL_MIDI_ASSIGNMENT CC="33" Note="0" Channel="0" MaxValue="127" MinValue="0" ControlPath="/frmParameterPages/pRight/rbParamPage" ControlIndex="1"/>
    <CTRL_MIDI_ASSIGNMENT CC="34" Note="0" Channel="0" MaxValue="127" MinValue="0" ControlPath="/frmParameterPages/pRight/rbParamPage" ControlIndex="2"/>
    <CTRL_MIDI_ASSIGNMENT CC="36" Note="0" Channel="0" MaxValue="127" MinValue="0" ControlPath="/frmParameterPages/pRight/rbParamPage" ControlIndex="4"/>
    <CTRL_MIDI_ASSIGNMENT CC="35" Note="0" Channel="0" MaxValue="127" MinValue="0" ControlPath="/frmParameterPages/pRight/rbParamPage" ControlIndex="3"/>
    <CTRL_MIDI_ASSIGNMENT CC="101" Note="0" Channel="0" MaxValue="127" MinValue="0" ControlPath="/frmParameterPages/pBottom/rbSlot" ControlIndex="0"/>
    <CTRL_MIDI_ASSIGNMENT CC="102" Note="0" Channel="0" MaxValue="127" MinValue="0" ControlPath="/frmParameterPages/pBottom/rbSlot" ControlIndex="1"/>
    <CTRL_MIDI_ASSIGNMENT CC="103" Note="0" Channel="0" MaxValue="127" MinValue="0" ControlPath="/frmParameterPages/pBottom/rbSlot" ControlIndex="2"/>
    <CTRL_MIDI_ASSIGNMENT CC="104" Note="0" Channel="0" MaxValue="127" MinValue="0" ControlPath="/frmParameterPages/pBottom/rbSlot" ControlIndex="3"/>
    <CTRL_MIDI_ASSIGNMENT CC="64" Note="0" Channel="0" MaxValue="127" MinValue="0" ControlPath="/frmPatchManager/Panel1/pSlot/btEnable" ControlIndex="0"/>
    <CTRL_MIDI_ASSIGNMENT CC="65" Note="0" Channel="0" MaxValue="127" MinValue="0" ControlPath="/frmPatchManager/Panel1/pSlot/btKeyboard" ControlIndex="0"/>
    <CTRL_MIDI_ASSIGNMENT CC="66" Note="0" Channel="0" MaxValue="127" MinValue="0" ControlPath="/frmPatchManager/Panel1/pSlot/btHold" ControlIndex="0"/>
    <CTRL_MIDI_ASSIGNMENT CC="37" Note="0" Channel="0" MaxValue="127" MinValue="0" ControlPath="/frmParameterPages/pBottom/rbParamColumn" ControlIndex="0"/>
    <CTRL_MIDI_ASSIGNMENT CC="38" Note="0" Channel="0" MaxValue="127" MinValue="0" ControlPath="/frmParameterPages/pBottom/rbParamColumn" ControlIndex="1"/>
    <CTRL_MIDI_ASSIGNMENT CC="39" Note="0" Channel="0" MaxValue="127" MinValue="0" ControlPath="/frmParameterPages/pBottom/rbParamColumn" ControlIndex="2"/>
    <CTRL_MIDI_ASSIGNMENT CC="40" Note="0" Channel="0" MaxValue="127" MinValue="0" ControlPath="/frmParameterPages/skP1" ControlIndex="0"/>
    <CTRL_MIDI_ASSIGNMENT CC="47" Note="0" Channel="0" MaxValue="127" MinValue="0" ControlPath="/frmParameterPages/skP8" ControlIndex="0"/>
  </CTRL_MIDI_ASSIGNMENT_LIST>
  <MainForm PosX="361" PosY="23" SizeX="1296" SizeY="948" Visible="True"/>
  <DirectorySettings G2oolsFolder="C:\Users\Bruno\Downloads\g2ools_15_190\g2ools-1.5\" ModuleHelpFile="C:\Program Files (x86)\Clavia\Nord Modular G2 v1.62\Nord Modular G2 Editor v1.62.chm"/>
  <PatchBrowserSettings BaseFolder="C:\Users\Bruno\Documents\Nord Modular Patches\G2 Patches\" SelectedTab="1" ExternalSortCol="0" InternalSortCol="0"/>
  <PatchBufferSettings Folder="C:\Users\Bruno\Documents\Nord Modular Patches\G2 Patches\Bruno\Blocks"/>
  <PatchBrowserForm PosX="100" PosY="100" SizeX="546" SizeY="438" Visible="False"/>
  <PatchManagerForm PosX="525" PosY="181" SizeX="727" SizeY="656" Visible="False"/>
  <PatchBufferForm PosX="0" PosY="151" SizeX="1166" SizeY="837" Visible="False"/>
  <SettingsForm PosX="752" PosY="258" SizeX="528" SizeY="466" Visible="False"/>
  <ParameterPagesForm PosX="1041" PosY="80" SizeX="575" SizeY="180" Visible="False"/>
  <PatchSettingsForm PosX="248" PosY="323" SizeX="608" SizeY="185" Visible="False"/>
  <EditorToolsForm PosX="977" PosY="565" SizeX="151" SizeY="261" Visible="False"/>
  <PatchNotesForm PosX="0" PosY="55" SizeX="611" SizeY="514" Visible="False"/>
</G2_Editor_settings>
